apk_builder/__init__.py
apk_builder/core.py
apk_website_converter-0.1.6.dist-info/METADATA
apk_website_converter-0.1.6.dist-info/WHEEL
apk_website_converter-0.1.6.dist-info/top_level.txt
apk_website_converter-0.1.6.dist-info/RECORD
