Metadata-Version: 2.4
Name: apk-website-converter
Version: 0.1.6
Summary: A library to convert website URLs into Android APKs using Apktool.
Home-page: https://github.com/shaiksadikjanu/apk-builder
Author: SHAIKJANU
Author-email: shaikjanu08012007@gmail.com
Classifier: Programming Language :: Python :: 3
Classifier: License :: OSI Approved :: MIT License
Classifier: Operating System :: OS Independent
Requires-Python: >=3.6
Requires-Dist: Pillow
Dynamic: author
Dynamic: author-email
Dynamic: classifier
Dynamic: description
Dynamic: description-content-type
Dynamic: home-page
Dynamic: requires-dist
Dynamic: requires-python
Dynamic: summary
